Testbenchs Verilog/cronometro/src/cronometro_all.v
module cronometro(reset, enable, clk, s0, s1, m0, m1, h);
    
    input wire reset, enable, clk;
    output [3:0] s0, s1, m0, m1, h;

    wire cs0, cs1, csm0, cm1, ch;

    upcountto9 upcountto9_s0(reset,clk,enable,s0,cs0);
    upcountto6 upcountto6_s1(reset,cs0,enable,s1,cs1);
    upcountto9 upcountto9_m0(reset,cs1,enable,m0,cm0);
    upcountto6 upcountto6_m1(reset,cm0,enable,m1,cm1);
    upcountto9 upcountto6_h(reset,cm1,enable,h,ch);

endmodule

module upcountto9(Reset, Clock, Enable, Salida, carry);

    input Reset, Clock, Enable;
    output reg [3:0] Salida;
    output reg carry;

    initial
    begin
        Salida <= 4'b0000;
        carry <= 0;
    end 

    always @(posedge Reset or posedge Clock) 
        if(Reset)
            Salida <= 4'b0000; //Si Reset es 1 pongo un 0 en binario de 4 bits
            else if (Enable && Salida < 4'b1001) //Si no llegue al 9, sigo contando
                begin
					Salida <= Salida + 1;
					carry<=0;
                end
					else if (Enable && (Salida == 4'b1001)) //Si llegue al 9, reinicio
                    begin 
						    Salida <= 4'b0000;
							carry<=1;
							end
endmodule

module upcountto6(Reset, Clock, Enable, Salida, carry);

    input Reset, Clock, Enable;
    output reg [3:0] Salida;
    output reg carry;

    initial
    begin
        Salida <= 4'b0000;
        carry <= 0;
    end 

    always @(posedge Reset or posedge Clock) 
        if(Reset)
            Salida <= 4'b0000; //Si Reset es 1 pongo un 0 en binario de 4 bits
            else if (Enable && Salida < 4'b0101) //Si no llegue al 5, sigo contando
                begin
					Salida <= Salida + 1;
					carry<=0;
                end
					else if (Enable && (Salida == 4'b0101)) //Si llegue al 5, reinicio
                    begin 
						    Salida <= 4'b0000;
							carry<=1;
							end
endmodule

Testbenchs Verilog/cronometro/src/clock_gen.v
`timescale 10s / 100ms

module clock_gen(clk);
	parameter PERIOD = 0.1;

	output reg clk;

	always
		begin: CLOCK_DRIVER
			clk <= 1'b0;
			#(PERIOD/2);
			clk <= 1'b1;
			#(PERIOD/2);
		end
endmodule

Testbenchs Verilog/cronometro/src/tb.v
`include "src/cronometro_all.v"
`include "src/clock_gen.v"

module tb;
    wire clk;
    wire [3:0] s0, s1, m0, m1, h;
    reg enable, reset;

    clock_gen clock0(clk);
    cronometro cronometro0(reset, enable, clk, s0, s1, m0, m1, h);

    initial
    begin
        enable <= 0;
        reset <=1;
        #1
        reset <= 0;
        enable <= 1;
        #500
        $finish;
    end

    reg[8*64:0] dumpfile_path = "output.vcd";

    initial begin
        $dumpfile(dumpfile_path);
        $dumpvars(0, tb);
    end
endmodule

Testbenchs Verilog/cronometro/output.vcd
$date
	Wed Nov 21 23:43:46 2018
$end
$version
	Icarus Verilog
$end
$timescale
	100ms
$end
$scope module tb $end
$var wire 4 ! s1 [3:0] $end
$var wire 4 " s0 [3:0] $end
$var wire 4 # m1 [3:0] $end
$var wire 4 $ m0 [3:0] $end
$var wire 4 % h [3:0] $end
$var wire 1 & clk $end
$var reg 513 ' dumpfile_path [512:0] $end
$var reg 1 ( enable $end
$var reg 1 ) reset $end
$scope module clock0 $end
$var reg 1 & clk $end
$scope begin CLOCK_DRIVER $end
$upscope $end
$upscope $end
$scope module cronometro0 $end
$var wire 1 & clk $end
$var wire 1 ( enable $end
$var wire 1 ) reset $end
$var wire 4 * s1 [3:0] $end
$var wire 4 + s0 [3:0] $end
$var wire 4 , m1 [3:0] $end
$var wire 4 - m0 [3:0] $end
$var wire 4 . h [3:0] $end
$var wire 1 / cs1 $end
$var wire 1 0 cs0 $end
$var wire 1 1 cm1 $end
$var wire 1 2 cm0 $end
$var wire 1 3 ch $end
$scope module upcountto6_h $end
$var wire 1 ( Enable $end
$var wire 1 ) Reset $end
$var wire 1 1 Clock $end
$var reg 4 4 Salida [3:0] $end
$var reg 1 3 carry $end
$upscope $end
$scope module upcountto6_m1 $end
$var wire 1 ( Enable $end
$var wire 1 ) Reset $end
$var wire 1 2 Clock $end
$var reg 4 5 Salida [3:0] $end
$var reg 1 1 carry $end
$upscope $end
$scope module upcountto6_s1 $end
$var wire 1 ( Enable $end
$var wire 1 ) Reset $end
$var wire 1 0 Clock $end
$var reg 4 6 Salida [3:0] $end
$var reg 1 / carry $end
$upscope $end
$scope module upcountto9_m0 $end
$var wire 1 / Clock $end
$var wire 1 ( Enable $end
$var wire 1 ) Reset $end
$var reg 4 7 Salida [3:0] $end
$var reg 1 2 carry $end
$upscope $end
$scope module upcountto9_s0 $end
$var wire 1 & Clock $end
$var wire 1 ( Enable $end
$var wire 1 ) Reset $end
$var reg 4 8 Salida [3:0] $end
$var reg 1 0 carry $end
$upscope $end
$upscope $end
$upscope $end
$enddefinitions $end
#0
$dumpvars
b0 8
b0 7
b0 6
b0 5
b0 4
03
02
01
00
0/
b0 .
b0 -
b0 ,
b0 +
b0 *
1)
0(
b1101111011101010111010001110000011101010111010000101110011101100110001101100100 '
0&
b0 %
b0 $
b0 #
b0 "
b0 !
$end
#5
1&
#10
0&
#15
1&
#20
0&
#25
1&
#30
0&
#35
1&
#40
0&
#45
1&
#50
0&
#55
1&
#60
0&
#65
1&
#70
0&
#75
1&
#80
0&
#85
1&
#90
0&
#95
1&
#100
0&
1(
0)
#105
b1 "
b1 +
b1 8
1&
#110
0&
#115
b10 "
b10 +
b10 8
1&
#120
0&
#125
b11 "
b11 +
b11 8
1&
#130
0&
#135
b100 "
b100 +
b100 8
1&
#140
0&
#145
b101 "
b101 +
b101 8
1&
#150
0&
#155
b110 "
b110 +
b110 8
1&
#160
0&
#165
b111 "
b111 +
b111 8
1&
#170
0&
#175
b1000 "
b1000 +
b1000 8
1&
#180
0&
#185
b1001 "
b1001 +
b1001 8
1&
#190
0&
#195
b1 !
b1 *
b1 6
10
b0 "
b0 +
b0 8
1&
#200
0&
#205
00
b1 "
b1 +
b1 8
1&
#210
0&
#215
b10 "
b10 +
b10 8
1&
#220
0&
#225
b11 "
b11 +
b11 8
1&
#230
0&
#235
b100 "
b100 +
b100 8
1&
#240
0&
#245
b101 "
b101 +
b101 8
1&
#250
0&
#255
b110 "
b110 +
b110 8
1&
#260
0&
#265
b111 "
b111 +
b111 8
1&
#270
0&
#275
b1000 "
b1000 +
b1000 8
1&
#280
0&
#285
b1001 "
b1001 +
b1001 8
1&
#290
0&
#295
b10 !
b10 *
b10 6
10
b0 "
b0 +
b0 8
1&
#300
0&
#305
00
b1 "
b1 +
b1 8
1&
#310
0&
#315
b10 "
b10 +
b10 8
1&
#320
0&
#325
b11 "
b11 +
b11 8
1&
#330
0&
#335
b100 "
b100 +
b100 8
1&
#340
0&
#345
b101 "
b101 +
b101 8
1&
#350
0&
#355
b110 "
b110 +
b110 8
1&
#360
0&
#365
b111 "
b111 +
b111 8
1&
#370
0&
#375
b1000 "
b1000 +
b1000 8
1&
#380
0&
#385
b1001 "
b1001 +
b1001 8
1&
#390
0&
#395
b11 !
b11 *
b11 6
10
b0 "
b0 +
b0 8
1&
#400
0&
#405
00
b1 "
b1 +
b1 8
1&
#410
0&
#415
b10 "
b10 +
b10 8
1&
#420
0&
#425
b11 "
b11 +
b11 8
1&
#430
0&
#435
b100 "
b100 +
b100 8
1&
#440
0&
#445
b101 "
b101 +
b101 8
1&
#450
0&
#455
b110 "
b110 +
b110 8
1&
#460
0&
#465
b111 "
b111 +
b111 8
1&
#470
0&
#475
b1000 "
b1000 +
b1000 8
1&
#480
0&
#485
b1001 "
b1001 +
b1001 8
1&
#490
0&
#495
b100 !
b100 *
b100 6
10
b0 "
b0 +
b0 8
1&
#500
0&
#505
00
b1 "
b1 +
b1 8
1&
#510
0&
#515
b10 "
b10 +
b10 8
1&
#520
0&
#525
b11 "
b11 +
b11 8
1&
#530
0&
#535
b100 "
b100 +
b100 8
1&
#540
0&
#545
b101 "
b101 +
b101 8
1&
#550
0&
#555
b110 "
b110 +
b110 8
1&
#560
0&
#565
b111 "
b111 +
b111 8
1&
#570
0&
#575
b1000 "
b1000 +
b1000 8
1&
#580
0&
#585
b1001 "
b1001 +
b1001 8
1&
#590
0&
#595
b101 !
b101 *
b101 6
10
b0 "
b0 +
b0 8
1&
#600
0&
#605
00
b1 "
b1 +
b1 8
1&
#610
0&
#615
b10 "
b10 +
b10 8
1&
#620
0&
#625
b11 "
b11 +
b11 8
1&
#630
0&
#635
b100 "
b100 +
b100 8
1&
#640
0&
#645
b101 "
b101 +
b101 8
1&
#650
0&
#655
b110 "
b110 +
b110 8
1&
#660
0&
#665
b111 "
b111 +
b111 8
1&
#670
0&
#675
b1000 "
b1000 +
b1000 8
1&
#680
0&
#685
b1001 "
b1001 +
b1001 8
1&
#690
0&
#695
b1 $
b1 -
b1 7
1/
b0 !
b0 *
b0 6
10
b0 "
b0 +
b0 8
1&
#700
0&
#705
00
b1 "
b1 +
b1 8
1&
#710
0&
#715
b10 "
b10 +
b10 8
1&
#720
0&
#725
b11 "
b11 +
b11 8
1&
#730
0&
#735
b100 "
b100 +
b100 8
1&
#740
0&
#745
b101 "
b101 +
b101 8
1&
#750
0&
#755
b110 "
b110 +
b110 8
1&
#760
0&
#765
b111 "
b111 +
b111 8
1&
#770
0&
#775
b1000 "
b1000 +
b1000 8
1&
#780
0&
#785
b1001 "
b1001 +
b1001 8
1&
#790
0&
#795
0/
b1 !
b1 *
b1 6
10
b0 "
b0 +
b0 8
1&
#800
0&
#805
00
b1 "
b1 +
b1 8
1&
#810
0&
#815
b10 "
b10 +
b10 8
1&
#820
0&
#825
b11 "
b11 +
b11 8
1&
#830
0&
#835
b100 "
b100 +
b100 8
1&
#840
0&
#845
b101 "
b101 +
b101 8
1&
#850
0&
#855
b110 "
b110 +
b110 8
1&
#860
0&
#865
b111 "
b111 +
b111 8
1&
#870
0&
#875
b1000 "
b1000 +
b1000 8
1&
#880
0&
#885
b1001 "
b1001 +
b1001 8
1&
#890
0&
#895
b10 !
b10 *
b10 6
10
b0 "
b0 +
b0 8
1&
#900
0&
#905
00
b1 "
b1 +
b1 8
1&
#910
0&
#915
b10 "
b10 +
b10 8
1&
#920
0&
#925
b11 "
b11 +
b11 8
1&
#930
0&
#935
b100 "
b100 +
b100 8
1&
#940
0&
#945
b101 "
b101 +
b101 8
1&
#950
0&
#955
b110 "
b110 +
b110 8
1&
#960
0&
#965
b111 "
b111 +
b111 8
1&
#970
0&
#975
b1000 "
b1000 +
b1000 8
1&
#980
0&
#985
b1001 "
b1001 +
b1001 8
1&
#990
0&
#995
b11 !
b11 *
b11 6
10
b0 "
b0 +
b0 8
1&
#1000
0&
#1005
00
b1 "
b1 +
b1 8
1&
#1010
0&
#1015
b10 "
b10 +
b10 8
1&
#1020
0&
#1025
b11 "
b11 +
b11 8
1&
#1030
0&
#1035
b100 "
b100 +
b100 8
1&
#1040
0&
#1045
b101 "
b101 +
b101 8
1&
#1050
0&
#1055
b110 "
b110 +
b110 8
1&
#1060
0&
#1065
b111 "
b111 +
b111 8
1&
#1070
0&
#1075
b1000 "
b1000 +
b1000 8
1&
#1080
0&
#1085
b1001 "
b1001 +
b1001 8
1&
#1090
0&
#1095
b100 !
b100 *
b100 6
10
b0 "
b0 +
b0 8
1&
#1100
0&
#1105
00
b1 "
b1 +
b1 8
1&
#1110
0&
#1115
b10 "
b10 +
b10 8
1&
#1120
0&
#1125
b11 "
b11 +
b11 8
1&
#1130
0&
#1135
b100 "
b100 +
b100 8
1&
#1140
0&
#1145
b101 "
b101 +
b101 8
1&
#1150
0&
#1155
b110 "
b110 +
b110 8
1&
#1160
0&
#1165
b111 "
b111 +
b111 8
1&
#1170
0&
#1175
b1000 "
b1000 +
b1000 8
1&
#1180
0&
#1185
b1001 "
b1001 +
b1001 8
1&
#1190
0&
#1195
b101 !
b101 *
b101 6
10
b0 "
b0 +
b0 8
1&
#1200
0&
#1205
00
b1 "
b1 +
b1 8
1&
#1210
0&
#1215
b10 "
b10 +
b10 8
1&
#1220
0&
#1225
b11 "
b11 +
b11 8
1&
#1230
0&
#1235
b100 "
b100 +
b100 8
1&
#1240
0&
#1245
b101 "
b101 +
b101 8
1&
#1250
0&
#1255
b110 "
b110 +
b110 8
1&
#1260
0&
#1265
b111 "
b111 +
b111 8
1&
#1270
0&
#1275
b1000 "
b1000 +
b1000 8
1&
#1280
0&
#1285
b1001 "
b1001 +
b1001 8
1&
#1290
0&
#1295
b10 $
b10 -
b10 7
1/
b0 !
b0 *
b0 6
10
b0 "
b0 +
b0 8
1&
#1300
0&
#1305
00
b1 "
b1 +
b1 8
1&
#1310
0&
#1315
b10 "
b10 +
b10 8
1&
#1320
0&
#1325
b11 "
b11 +
b11 8
1&
#1330
0&
#1335
b100 "
b100 +
b100 8
1&
#1340
0&
#1345
b101 "
b101 +
b101 8
1&
#1350
0&
#1355
b110 "
b110 +
b110 8
1&
#1360
0&
#1365
b111 "
b111 +
b111 8
1&
#1370
0&
#1375
b1000 "
b1000 +
b1000 8
1&
#1380
0&
#1385
b1001 "
b1001 +
b1001 8
1&
#1390
0&
#1395
0/
b1 !
b1 *
b1 6
10
b0 "
b0 +
b0 8
1&
#1400
0&
#1405
00
b1 "
b1 +
b1 8
1&
#1410
0&
#1415
b10 "
b10 +
b10 8
1&
#1420
0&
#1425
b11 "
b11 +
b11 8
1&
#1430
0&
#1435
b100 "
b100 +
b100 8
1&
#1440
0&
#1445
b101 "
b101 +
b101 8
1&
#1450
0&
#1455
b110 "
b110 +
b110 8
1&
#1460
0&
#1465
b111 "
b111 +
b111 8
1&
#1470
0&
#1475
b1000 "
b1000 +
b1000 8
1&
#1480
0&
#1485
b1001 "
b1001 +
b1001 8
1&
#1490
0&
#1495
b10 !
b10 *
b10 6
10
b0 "
b0 +
b0 8
1&
#1500
0&
#1505
00
b1 "
b1 +
b1 8
1&
#1510
0&
#1515
b10 "
b10 +
b10 8
1&
#1520
0&
#1525
b11 "
b11 +
b11 8
1&
#1530
0&
#1535
b100 "
b100 +
b100 8
1&
#1540
0&
#1545
b101 "
b101 +
b101 8
1&
#1550
0&
#1555
b110 "
b110 +
b110 8
1&
#1560
0&
#1565
b111 "
b111 +
b111 8
1&
#1570
0&
#1575
b1000 "
b1000 +
b1000 8
1&
#1580
0&
#1585
b1001 "
b1001 +
b1001 8
1&
#1590
0&
#1595
b11 !
b11 *
b11 6
10
b0 "
b0 +
b0 8
1&
#1600
0&
#1605
00
b1 "
b1 +
b1 8
1&
#1610
0&
#1615
b10 "
b10 +
b10 8
1&
#1620
0&
#1625
b11 "
b11 +
b11 8
1&
#1630
0&
#1635
b100 "
b100 +
b100 8
1&
#1640
0&
#1645
b101 "
b101 +
b101 8
1&
#1650
0&
#1655
b110 "
b110 +
b110 8
1&
#1660
0&
#1665
b111 "
b111 +
b111 8
1&
#1670
0&
#1675
b1000 "
b1000 +
b1000 8
1&
#1680
0&
#1685
b1001 "
b1001 +
b1001 8
1&
#1690
0&
#1695
b100 !
b100 *
b100 6
10
b0 "
b0 +
b0 8
1&
#1700
0&
#1705
00
b1 "
b1 +
b1 8
1&
#1710
0&
#1715
b10 "
b10 +
b10 8
1&
#1720
0&
#1725
b11 "
b11 +
b11 8
1&
#1730
0&
#1735
b100 "
b100 +
b100 8
1&
#1740
0&
#1745
b101 "
b101 +
b101 8
1&
#1750
0&
#1755
b110 "
b110 +
b110 8
1&
#1760
0&
#1765
b111 "
b111 +
b111 8
1&
#1770
0&
#1775
b1000 "
b1000 +
b1000 8
1&
#1780
0&
#1785
b1001 "
b1001 +
b1001 8
1&
#1790
0&
#1795
b101 !
b101 *
b101 6
10
b0 "
b0 +
b0 8
1&
#1800
0&
#1805
00
b1 "
b1 +
b1 8
1&
#1810
0&
#1815
b10 "
b10 +
b10 8
1&
#1820
0&
#1825
b11 "
b11 +
b11 8
1&
#1830
0&
#1835
b100 "
b100 +
b100 8
1&
#1840
0&
#1845
b101 "
b101 +
b101 8
1&
#1850
0&
#1855
b110 "
b110 +
b110 8
1&
#1860
0&
#1865
b111 "
b111 +
b111 8
1&
#1870
0&
#1875
b1000 "
b1000 +
b1000 8
1&
#1880
0&
#1885
b1001 "
b1001 +
b1001 8
1&
#1890
0&
#1895
b11 $
b11 -
b11 7
1/
b0 !
b0 *
b0 6
10
b0 "
b0 +
b0 8
1&
#1900
0&
#1905
00
b1 "
b1 +
b1 8
1&
#1910
0&
#1915
b10 "
b10 +
b10 8
1&
#1920
0&
#1925
b11 "
b11 +
b11 8
1&
#1930
0&
#1935
b100 "
b100 +
b100 8
1&
#1940
0&
#1945
b101 "
b101 +
b101 8
1&
#1950
0&
#1955
b110 "
b110 +
b110 8
1&
#1960
0&
#1965
b111 "
b111 +
b111 8
1&
#1970
0&
#1975
b1000 "
b1000 +
b1000 8
1&
#1980
0&
#1985
b1001 "
b1001 +
b1001 8
1&
#1990
0&
#1995
0/
b1 !
b1 *
b1 6
10
b0 "
b0 +
b0 8
1&
#2000
0&
#2005
00
b1 "
b1 +
b1 8
1&
#2010
0&
#2015
b10 "
b10 +
b10 8
1&
#2020
0&
#2025
b11 "
b11 +
b11 8
1&
#2030
0&
#2035
b100 "
b100 +
b100 8
1&
#2040
0&
#2045
b101 "
b101 +
b101 8
1&
#2050
0&
#2055
b110 "
b110 +
b110 8
1&
#2060
0&
#2065
b111 "
b111 +
b111 8
1&
#2070
0&
#2075
b1000 "
b1000 +
b1000 8
1&
#2080
0&
#2085
b1001 "
b1001 +
b1001 8
1&
#2090
0&
#2095
b10 !
b10 *
b10 6
10
b0 "
b0 +
b0 8
1&
#2100
0&
#2105
00
b1 "
b1 +
b1 8
1&
#2110
0&
#2115
b10 "
b10 +
b10 8
1&
#2120
0&
#2125
b11 "
b11 +
b11 8
1&
#2130
0&
#2135
b100 "
b100 +
b100 8
1&
#2140
0&
#2145
b101 "
b101 +
b101 8
1&
#2150
0&
#2155
b110 "
b110 +
b110 8
1&
#2160
0&
#2165
b111 "
b111 +
b111 8
1&
#2170
0&
#2175
b1000 "
b1000 +
b1000 8
1&
#2180
0&
#2185
b1001 "
b1001 +
b1001 8
1&
#2190
0&
#2195
b11 !
b11 *
b11 6
10
b0 "
b0 +
b0 8
1&
#2200
0&
#2205
00
b1 "
b1 +
b1 8
1&
#2210
0&
#2215
b10 "
b10 +
b10 8
1&
#2220
0&
#2225
b11 "
b11 +
b11 8
1&
#2230
0&
#2235
b100 "
b100 +
b100 8
1&
#2240
0&
#2245
b101 "
b101 +
b101 8
1&
#2250
0&
#2255
b110 "
b110 +
b110 8
1&
#2260
0&
#2265
b111 "
b111 +
b111 8
1&
#2270
0&
#2275
b1000 "
b1000 +
b1000 8
1&
#2280
0&
#2285
b1001 "
b1001 +
b1001 8
1&
#2290
0&
#2295
b100 !
b100 *
b100 6
10
b0 "
b0 +
b0 8
1&
#2300
0&
#2305
00
b1 "
b1 +
b1 8
1&
#2310
0&
#2315
b10 "
b10 +
b10 8
1&
#2320
0&
#2325
b11 "
b11 +
b11 8
1&
#2330
0&
#2335
b100 "
b100 +
b100 8
1&
#2340
0&
#2345
b101 "
b101 +
b101 8
1&
#2350
0&
#2355
b110 "
b110 +
b110 8
1&
#2360
0&
#2365
b111 "
b111 +
b111 8
1&
#2370
0&
#2375
b1000 "
b1000 +
b1000 8
1&
#2380
0&
#2385
b1001 "
b1001 +
b1001 8
1&
#2390
0&
#2395
b101 !
b101 *
b101 6
10
b0 "
b0 +
b0 8
1&
#2400
0&
#2405
00
b1 "
b1 +
b1 8
1&
#2410
0&
#2415
b10 "
b10 +
b10 8
1&
#2420
0&
#2425
b11 "
b11 +
b11 8
1&
#2430
0&
#2435
b100 "
b100 +
b100 8
1&
#2440
0&
#2445
b101 "
b101 +
b101 8
1&
#2450
0&
#2455
b110 "
b110 +
b110 8
1&
#2460
0&
#2465
b111 "
b111 +
b111 8
1&
#2470
0&
#2475
b1000 "
b1000 +
b1000 8
1&
#2480
0&
#2485
b1001 "
b1001 +
b1001 8
1&
#2490
0&
#2495
b100 $
b100 -
b100 7
1/
b0 !
b0 *
b0 6
10
b0 "
b0 +
b0 8
1&
#2500
0&
#2505
00
b1 "
b1 +
b1 8
1&
#2510
0&
#2515
b10 "
b10 +
b10 8
1&
#2520
0&
#2525
b11 "
b11 +
b11 8
1&
#2530
0&
#2535
b100 "
b100 +
b100 8
1&
#2540
0&
#2545
b101 "
b101 +
b101 8
1&
#2550
0&
#2555
b110 "
b110 +
b110 8
1&
#2560
0&
#2565
b111 "
b111 +
b111 8
1&
#2570
0&
#2575
b1000 "
b1000 +
b1000 8
1&
#2580
0&
#2585
b1001 "
b1001 +
b1001 8
1&
#2590
0&
#2595
0/
b1 !
b1 *
b1 6
10
b0 "
b0 +
b0 8
1&
#2600
0&
#2605
00
b1 "
b1 +
b1 8
1&
#2610
0&
#2615
b10 "
b10 +
b10 8
1&
#2620
0&
#2625
b11 "
b11 +
b11 8
1&
#2630
0&
#2635
b100 "
b100 +
b100 8
1&
#2640
0&
#2645
b101 "
b101 +
b101 8
1&
#2650
0&
#2655
b110 "
b110 +
b110 8
1&
#2660
0&
#2665
b111 "
b111 +
b111 8
1&
#2670
0&
#2675
b1000 "
b1000 +
b1000 8
1&
#2680
0&
#2685
b1001 "
b1001 +
b1001 8
1&
#2690
0&
#2695
b10 !
b10 *
b10 6
10
b0 "
b0 +
b0 8
1&
#2700
0&
#2705
00
b1 "
b1 +
b1 8
1&
#2710
0&
#2715
b10 "
b10 +
b10 8
1&
#2720
0&
#2725
b11 "
b11 +
b11 8
1&
#2730
0&
#2735
b100 "
b100 +
b100 8
1&
#2740
0&
#2745
b101 "
b101 +
b101 8
1&
#2750
0&
#2755
b110 "
b110 +
b110 8
1&
#2760
0&
#2765
b111 "
b111 +
b111 8
1&
#2770
0&
#2775
b1000 "
b1000 +
b1000 8
1&
#2780
0&
#2785
b1001 "
b1001 +
b1001 8
1&
#2790
0&
#2795
b11 !
b11 *
b11 6
10
b0 "
b0 +
b0 8
1&
#2800
0&
#2805
00
b1 "
b1 +
b1 8
1&
#2810
0&
#2815
b10 "
b10 +
b10 8
1&
#2820
0&
#2825
b11 "
b11 +
b11 8
1&
#2830
0&
#2835
b100 "
b100 +
b100 8
1&
#2840
0&
#2845
b101 "
b101 +
b101 8
1&
#2850
0&
#2855
b110 "
b110 +
b110 8
1&
#2860
0&
#2865
b111 "
b111 +
b111 8
1&
#2870
0&
#2875
b1000 "
b1000 +
b1000 8
1&
#2880
0&
#2885
b1001 "
b1001 +
b1001 8
1&
#2890
0&
#2895
b100 !
b100 *
b100 6
10
b0 "
b0 +
b0 8
1&
#2900
0&
#2905
00
b1 "
b1 +
b1 8
1&
#2910
0&
#2915
b10 "
b10 +
b10 8
1&
#2920
0&
#2925
b11 "
b11 +
b11 8
1&
#2930
0&
#2935
b100 "
b100 +
b100 8
1&
#2940
0&
#2945
b101 "
b101 +
b101 8
1&
#2950
0&
#2955
b110 "
b110 +
b110 8
1&
#2960
0&
#2965
b111 "
b111 +
b111 8
1&
#2970
0&
#2975
b1000 "
b1000 +
b1000 8
1&
#2980
0&
#2985
b1001 "
b1001 +
b1001 8
1&
#2990
0&
#2995
b101 !
b101 *
b101 6
10
b0 "
b0 +
b0 8
1&
#3000
0&
#3005
00
b1 "
b1 +
b1 8
1&
#3010
0&
#3015
b10 "
b10 +
b10 8
1&
#3020
0&
#3025
b11 "
b11 +
b11 8
1&
#3030
0&
#3035
b100 "
b100 +
b100 8
1&
#3040
0&
#3045
b101 "
b101 +
b101 8
1&
#3050
0&
#3055
b110 "
b110 +
b110 8
1&
#3060
0&
#3065
b111 "
b111 +
b111 8
1&
#3070
0&
#3075
b1000 "
b1000 +
b1000 8
1&
#3080
0&
#3085
b1001 "
b1001 +
b1001 8
1&
#3090
0&
#3095
b101 $
b101 -
b101 7
1/
b0 !
b0 *
b0 6
10
b0 "
b0 +
b0 8
1&
#3100
0&
#3105
00
b1 "
b1 +
b1 8
1&
#3110
0&
#3115
b10 "
b10 +
b10 8
1&
#3120
0&
#3125
b11 "
b11 +
b11 8
1&
#3130
0&
#3135
b100 "
b100 +
b100 8
1&
#3140
0&
#3145
b101 "
b101 +
b101 8
1&
#3150
0&
#3155
b110 "
b110 +
b110 8
1&
#3160
0&
#3165
b111 "
b111 +
b111 8
1&
#3170
0&
#3175
b1000 "
b1000 +
b1000 8
1&
#3180
0&
#3185
b1001 "
b1001 +
b1001 8
1&
#3190
0&
#3195
0/
b1 !
b1 *
b1 6
10
b0 "
b0 +
b0 8
1&
#3200
0&
#3205
00
b1 "
b1 +
b1 8
1&
#3210
0&
#3215
b10 "
b10 +
b10 8
1&
#3220
0&
#3225
b11 "
b11 +
b11 8
1&
#3230
0&
#3235
b100 "
b100 +
b100 8
1&
#3240
0&
#3245
b101 "
b101 +
b101 8
1&
#3250
0&
#3255
b110 "
b110 +
b110 8
1&
#3260
0&
#3265
b111 "
b111 +
b111 8
1&
#3270
0&
#3275
b1000 "
b1000 +
b1000 8
1&
#3280
0&
#3285
b1001 "
b1001 +
b1001 8
1&
#3290
0&
#3295
b10 !
b10 *
b10 6
10
b0 "
b0 +
b0 8
1&
#3300
0&
#3305
00
b1 "
b1 +
b1 8
1&
#3310
0&
#3315
b10 "
b10 +
b10 8
1&
#3320
0&
#3325
b11 "
b11 +
b11 8
1&
#3330
0&
#3335
b100 "
b100 +
b100 8
1&
#3340
0&
#3345
b101 "
b101 +
b101 8
1&
#3350
0&
#3355
b110 "
b110 +
b110 8
1&
#3360
0&
#3365
b111 "
b111 +
b111 8
1&
#3370
0&
#3375
b1000 "
b1000 +
b1000 8
1&
#3380
0&
#3385
b1001 "
b1001 +
b1001 8
1&
#3390
0&
#3395
b11 !
b11 *
b11 6
10
b0 "
b0 +
b0 8
1&
#3400
0&
#3405
00
b1 "
b1 +
b1 8
1&
#3410
0&
#3415
b10 "
b10 +
b10 8
1&
#3420
0&
#3425
b11 "
b11 +
b11 8
1&
#3430
0&
#3435
b100 "
b100 +
b100 8
1&
#3440
0&
#3445
b101 "
b101 +
b101 8
1&
#3450
0&
#3455
b110 "
b110 +
b110 8
1&
#3460
0&
#3465
b111 "
b111 +
b111 8
1&
#3470
0&
#3475
b1000 "
b1000 +
b1000 8
1&
#3480
0&
#3485
b1001 "
b1001 +
b1001 8
1&
#3490
0&
#3495
b100 !
b100 *
b100 6
10
b0 "
b0 +
b0 8
1&
#3500
0&
#3505
00
b1 "
b1 +
b1 8
1&
#3510
0&
#3515
b10 "
b10 +
b10 8
1&
#3520
0&
#3525
b11 "
b11 +
b11 8
1&
#3530
0&
#3535
b100 "
b100 +
b100 8
1&
#3540
0&
#3545
b101 "
b101 +
b101 8
1&
#3550
0&
#3555
b110 "
b110 +
b110 8
1&
#3560
0&
#3565
b111 "
b111 +
b111 8
1&
#3570
0&
#3575
b1000 "
b1000 +
b1000 8
1&
#3580
0&
#3585
b1001 "
b1001 +
b1001 8
1&
#3590
0&
#3595
b101 !
b101 *
b101 6
10
b0 "
b0 +
b0 8
1&
#3600
0&
#3605
00
b1 "
b1 +
b1 8
1&
#3610
0&
#3615
b10 "
b10 +
b10 8
1&
#3620
0&
#3625
b11 "
b11 +
b11 8
1&
#3630
0&
#3635
b100 "
b100 +
b100 8
1&
#3640
0&
#3645
b101 "
b101 +
b101 8
1&
#3650
0&
#3655
b110 "
b110 +
b110 8
1&
#3660
0&
#3665
b111 "
b111 +
b111 8
1&
#3670
0&
#3675
b1000 "
b1000 +
b1000 8
1&
#3680
0&
#3685
b1001 "
b1001 +
b1001 8
1&
#3690
0&
#3695
b110 $
b110 -
b110 7
1/
b0 !
b0 *
b0 6
10
b0 "
b0 +
b0 8
1&
#3700
0&
#3705
00
b1 "
b1 +
b1 8
1&
#3710
0&
#3715
b10 "
b10 +
b10 8
1&
#3720
0&
#3725
b11 "
b11 +
b11 8
1&
#3730
0&
#3735
b100 "
b100 +
b100 8
1&
#3740
0&
#3745
b101 "
b101 +
b101 8
1&
#3750
0&
#3755
b110 "
b110 +
b110 8
1&
#3760
0&
#3765
b111 "
b111 +
b111 8
1&
#3770
0&
#3775
b1000 "
b1000 +
b1000 8
1&
#3780
0&
#3785
b1001 "
b1001 +
b1001 8
1&
#3790
0&
#3795
0/
b1 !
b1 *
b1 6
10
b0 "
b0 +
b0 8
1&
#3800
0&
#3805
00
b1 "
b1 +
b1 8
1&
#3810
0&
#3815
b10 "
b10 +
b10 8
1&
#3820
0&
#3825
b11 "
b11 +
b11 8
1&
#3830
0&
#3835
b100 "
b100 +
b100 8
1&
#3840
0&
#3845
b101 "
b101 +
b101 8
1&
#3850
0&
#3855
b110 "
b110 +
b110 8
1&
#3860
0&
#3865
b111 "
b111 +
b111 8
1&
#3870
0&
#3875
b1000 "
b1000 +
b1000 8
1&
#3880
0&
#3885
b1001 "
b1001 +
b1001 8
1&
#3890
0&
#3895
b10 !
b10 *
b10 6
10
b0 "
b0 +
b0 8
1&
#3900
0&
#3905
00
b1 "
b1 +
b1 8
1&
#3910
0&
#3915
b10 "
b10 +
b10 8
1&
#3920
0&
#3925
b11 "
b11 +
b11 8
1&
#3930
0&
#3935
b100 "
b100 +
b100 8
1&
#3940
0&
#3945
b101 "
b101 +
b101 8
1&
#3950
0&
#3955
b110 "
b110 +
b110 8
1&
#3960
0&
#3965
b111 "
b111 +
b111 8
1&
#3970
0&
#3975
b1000 "
b1000 +
b1000 8
1&
#3980
0&
#3985
b1001 "
b1001 +
b1001 8
1&
#3990
0&
#3995
b11 !
b11 *
b11 6
10
b0 "
b0 +
b0 8
1&
#4000
0&
#4005
00
b1 "
b1 +
b1 8
1&
#4010
0&
#4015
b10 "
b10 +
b10 8
1&
#4020
0&
#4025
b11 "
b11 +
b11 8
1&
#4030
0&
#4035
b100 "
b100 +
b100 8
1&
#4040
0&
