Testbenchs Verilog/segments/src/bin_to_segments.v
module bin_to_segments(segments, digit, enable);

    input enable;
    input [3:0] digit;
    output reg [6:0] segments;

    parameter   CERO = 7'b1111110, UNO = 7'b0110000, DOS = 7'b1101101, TRES = 7'b1111001, CUATRO = 7'b0110011, 
                CINCO = 7'b1011011, SEIS = 7'b1011111, SIETE = 7'b1110000, OCHO = 7'b1111111, NUEVE = 7'b1111011;

    always @ (*)
    begin
        if(enable == 1)
        begin
            case(digit)
                4'b0000: segments <= CERO;
                4'b0001: segments <= UNO;
                4'b0010: segments <= DOS;
                4'b0011: segments <= TRES;
                4'b0100: segments <= CUATRO;
                4'b0101: segments <= CINCO;
                4'b0110: segments <= SEIS;
                4'b0111: segments <= SIETE;
                4'b1000: segments <= OCHO;
                4'b1001: segments <= NUEVE;
            endcase
        end
        else segments <= CERO;
    end

endmodule

Testbenchs Verilog/segments/src/tb.v
`include "src/bin_to_segments.v"

module tb;

    wire [6:0] segments;
    reg [3:0] digit;
    reg enable;
    bin_to_segments bin_to_segments0(segments, digit, enable);

    initial
    begin
        enable = 0;
        #1
        enable = 1;
        #1
        digit = 0;
        #1
        digit = 1;
        #1
        digit = 2;
        #1
        digit = 3;
        #1
        digit = 4;
        #1
        digit = 5;
        #1
        digit = 6;
        #1
        digit = 7;
        #1
        digit = 8;
        #1
        digit = 9;
        #1
        $finish;
    end

    reg[8*64:0] dumpfile_path = "output.vcd";

    initial begin
        $dumpfile(dumpfile_path);
        $dumpvars(0, tb);
    end

endmodule

Testbenchs Verilog/segments/output.vcd
$date
	Tue Nov 20 04:17:22 2018
$end
$version
	Icarus Verilog
$end
$timescale
	1s
$end
$scope module tb $end
$var wire 7 ! segments [6:0] $end
$var reg 4 " digit [3:0] $end
$var reg 513 # dumpfile_path [512:0] $end
$var reg 1 $ enable $end
$scope module bin_to_segments0 $end
$var wire 4 % digit [3:0] $end
$var wire 1 $ enable $end
$var reg 7 & segments [6:0] $end
$upscope $end
$upscope $end
$enddefinitions $end
#0
$dumpvars
b1111110 &
bx %
0$
b1101111011101010111010001110000011101010111010000101110011101100110001101100100 #
bx "
b1111110 !
$end
#1
1$
#2
b0 "
b0 %
#3
b110000 !
b110000 &
b1 "
b1 %
#4
b1101101 !
b1101101 &
b10 "
b10 %
#5
b1111001 !
b1111001 &
b11 "
b11 %
#6
b110011 !
b110011 &
b100 "
b100 %
#7
b1011011 !
b1011011 &
b101 "
b101 %
#8
b1011111 !
b1011111 &
b110 "
b110 %
#9
b1110000 !
b1110000 &
b111 "
b111 %
#10
b1111111 !
b1111111 &
b1000 "
b1000 %
#11
b1111011 !
b1111011 &
b1001 "
b1001 %
