Testbenchs Verilog/fsm_boton/src/fsm_boton.v
// Esta fsm controla que los pulsadores
// generen una sola salida en el instante que se pulsan
// y no vuelvan a generar otra señal en tanto
// no se suelte y vuelva a presionar.

// Debe tener u clock tal que 'filtre' el rebote
// y tal que permita presionarlo repetidamente relativamente 'rapido'

module fsm_boton(clk, btn, signal);

    input clk, btn;
    output signal;

    wire clk, btn;
    reg signal;

    parameter IDLE = 1'b0, PRESSED = 1'b1;

    reg state, next_state;

    initial
    begin
        state <= IDLE;
        signal <= 0;
    end

    always @ (posedge clk)
    begin: FSM
    case(state)
        IDLE:       if(btn == 1'b1)
                    begin
                        state <= PRESSED;
                        signal <= 1;
                    end
                    else if(btn == 1'b0)
                    begin
                        state <= IDLE;
                        signal <=0;
                    end
        PRESSED:    if(btn == 1'b1)
                    begin
                        state <= PRESSED;
                        signal <= 0;
                    end
                    else if(btn == 1'b0)
                    begin
                        state <= IDLE;
                        signal <= 0;
                    end
        default:    state <= IDLE;
                    
    endcase
    end
endmodule

Testbenchs Verilog/fsm_enable/src/clock_gen.v
`timescale 100us / 100us

module clock_gen(clk);
	parameter PERIOD = 4;

	output reg clk;

	always
		begin: CLOCK_DRIVER
			clk <= 1'b0;
			#(PERIOD/2);
			clk <= 1'b1;
			#(PERIOD/2);
		end
endmodule

Testbenchs Verilog/fsm_boton/src/testbench_fsm_btn.v
`include "src/clock_gen.v"
`include "src/fsm_boton.v" 

module testbench_fsm;
    wire clk, signal;
    reg btn;

    clock_gen clock0(clk);
    fsm_boton fsm_boton0(clk, btn, signal);

    initial
    begin
        btn = 0;
        #3
        btn = 1;
        #10
        btn = 0;
        #10
        btn = 1;
        #10
        btn = 0;
        #10
        $finish;
    end

    reg[8*64:0] dumpfile_path = "output.vcd";

    initial begin
        $dumpfile(dumpfile_path);
        $dumpvars(0, testbench_fsm);
    end
endmodule

Testbenchs Verilog/fsm_boton/output.vcd
$date
	Mon Nov 19 21:12:33 2018
$end
$version
	Icarus Verilog
$end
$timescale
	100us
$end
$scope module testbench_fsm $end
$var wire 1 ! signal $end
$var wire 1 " clk $end
$var reg 1 # btn $end
$var reg 513 $ dumpfile_path [512:0] $end
$scope module clock0 $end
$var reg 1 " clk $end
$scope begin CLOCK_DRIVER $end
$upscope $end
$upscope $end
$scope module fsm_boton0 $end
$var wire 1 # btn $end
$var wire 1 " clk $end
$var reg 1 ! signal $end
$var reg 1 % state $end
$scope begin FSM $end
$upscope $end
$upscope $end
$upscope $end
$enddefinitions $end
#0
$dumpvars
0%
b1101111011101010111010001110000011101010111010000101110011101100110001101100100 $
0#
0"
0!
$end
#2
1"
#3
1#
#4
0"
#6
1!
1"
#7
1%
#8
0"
#10
0!
1"
#12
0"
#13
0#
#14
1"
#15
0%
#16
0"
#18
1"
#20
0"
#22
1"
#23
1#
#24
0"
#26
1!
1"
#27
1%
#28
0"
#30
0!
1"
#32
0"
#33
0#
#34
1"
#35
0%
